sushineAI/__init__.py
sushineAI/app.py
sushineAI/argument.py
sushineAI/component.py
sushineAI/services.py
sushineAI/utils/__init__.py
sushineAI/utils/ai_model.py
sushineAI/utils/file_operator.py
sushineAI/utils/messagemq.py
sushineAI/utils/model_operator.py
sushineAI/utils/storager.py
sushineAI/utils/translator.py
sushineAI-2.0.0.dist-info/DESCRIPTION.rst
sushineAI-2.0.0.dist-info/METADATA
sushineAI-2.0.0.dist-info/RECORD
sushineAI-2.0.0.dist-info/WHEEL
sushineAI-2.0.0.dist-info/metadata.json
sushineAI-2.0.0.dist-info/top_level.txt
